flashcards/__init__.py
flashcards/flashcards.py
flashcards/public/student-ui.css
flashcards/public/student-ui.js
flashcards/public/studio-ui.css
flashcards/public/studio-ui.js
flashcards/static/html/studio.html
flashcards/static/js/student.js
flashcards/static/js/studio.js
flashcardsxblock-1.0.2rc2.dist-info/licenses/LICENSE
flashcardsxblock-1.0.2rc2.dist-info/METADATA
flashcardsxblock-1.0.2rc2.dist-info/WHEEL
flashcardsxblock-1.0.2rc2.dist-info/entry_points.txt
flashcardsxblock-1.0.2rc2.dist-info/top_level.txt
flashcardsxblock-1.0.2rc2.dist-info/RECORD
