Metadata-Version: 2.4
Name: FlashcardsXBlock
Version: 1.0.2rc2
Summary: A Flashcards XBlock for Open edX.
License-Expression: MIT
Project-URL: Homepage, https://github.com/open-craft/FlashcardsXBlock
Keywords: Python,edx
Classifier: Development Status :: 5 - Production/Stable
Classifier: Framework :: Django
Classifier: Framework :: Django :: 4.2
Classifier: Intended Audience :: Developers
Classifier: Natural Language :: English
Classifier: Programming Language :: Python :: 3
Classifier: Programming Language :: Python :: 3.11
Requires-Python: >=3.11
License-File: LICENSE
Requires-Dist: XBlock
Dynamic: license-file
